Metadata-Version: 1.1
Name: django-shibboleth-session-auth
Version: 0.6.0
Summary: Simplistic Shibboleth integration for Django sessions
Home-page: https://github.com/esnet/shibboleth_session_auth
Author: Jon M. Dugan
Author-email: jdugan@es.net
License: BSD
Keywords: Django Shibboleth
Platform: UNKNOWN
Classifier: Development Status :: 4 - Beta
Classifier: Intended Audience :: Developers
Classifier: Programming Language :: Python :: 2.7
